.eslintignore
.eslintrc.js
.gitignore
.prettierignore
.prettierrc
Config
DEVELOPMENT.md
LICENSE
MANIFEST.in
NOTICE
README.md
RELEASE.md
babel.config.js
custom.d.ts
host_region_mapping.py
jest.config.base.js
jest.config.js
package-lock.json
package.json
pyproject.toml
requirements.txt
setup.py
tsconfig.json
amazon_sagemaker_jupyter_scheduler/__init__.py
amazon_sagemaker_jupyter_scheduler/_version.py
amazon_sagemaker_jupyter_scheduler/app_metadata.py
amazon_sagemaker_jupyter_scheduler/aws_config.py
amazon_sagemaker_jupyter_scheduler/clients.py
amazon_sagemaker_jupyter_scheduler/cron_util.py
amazon_sagemaker_jupyter_scheduler/deletable_resource.py
amazon_sagemaker_jupyter_scheduler/environment_detector.py
amazon_sagemaker_jupyter_scheduler/environments.py
amazon_sagemaker_jupyter_scheduler/error_util.py
amazon_sagemaker_jupyter_scheduler/extension.py
amazon_sagemaker_jupyter_scheduler/file_download_manager.py
amazon_sagemaker_jupyter_scheduler/file_uploader.py
amazon_sagemaker_jupyter_scheduler/handlers.py
amazon_sagemaker_jupyter_scheduler/host_region_mapping.json
amazon_sagemaker_jupyter_scheduler/internal_metadata_adapter.py
amazon_sagemaker_jupyter_scheduler/logging.py
amazon_sagemaker_jupyter_scheduler/model_converter.py
amazon_sagemaker_jupyter_scheduler/models.py
amazon_sagemaker_jupyter_scheduler/runtime_environment_parameters.py
amazon_sagemaker_jupyter_scheduler/s3_uri.py
amazon_sagemaker_jupyter_scheduler/scheduler.py
amazon_sagemaker_jupyter_scheduler/stack_trace_filter.py
amazon_sagemaker_jupyter_scheduler/utils.py
amazon_sagemaker_jupyter_scheduler.egg-info/PKG-INFO
amazon_sagemaker_jupyter_scheduler.egg-info/SOURCES.txt
amazon_sagemaker_jupyter_scheduler.egg-info/dependency_links.txt
amazon_sagemaker_jupyter_scheduler.egg-info/not-zip-safe
amazon_sagemaker_jupyter_scheduler.egg-info/requires.txt
amazon_sagemaker_jupyter_scheduler.egg-info/top_level.txt
amazon_sagemaker_jupyter_scheduler/advanced_environments/__init__.py
amazon_sagemaker_jupyter_scheduler/advanced_environments/base_advanced_environments.py
amazon_sagemaker_jupyter_scheduler/advanced_environments/sagemaker_advanced_environments.py
amazon_sagemaker_jupyter_scheduler/advanced_environments/sagemaker_studio_advanced_environment.py
amazon_sagemaker_jupyter_scheduler/labextension/package.json
