Metadata-Version: 2.1
Name: amazon-sagemaker-jupyter-scheduler
Version: 3.1.15
Summary: Amazon SageMaker Jupyter Scheduler based on the https://pypi.org/project/jupyter-scheduler/
Home-page: https://aws.amazon.com/sagemaker/
Author: Amazon
License: Apache 2.0
Keywords: Jupyter,JupyterLab,JupyterLab3,Scheduling Notebooks,Notebooks,Amazon Sagemaker
Platform: Linux
Platform: Mac OS X
Platform: Windows
Classifier: License :: OSI Approved :: Apache Software License
Classifier: Programming Language :: Python
Classifier: Programming Language :: Python :: 3.7
Classifier: Programming Language :: Python :: 3.8
Classifier: Programming Language :: Python :: 3.9
Classifier: Programming Language :: Python :: 3.10
Classifier: Framework :: Jupyter
Requires-Python: >=3.7
Provides-Extra: dev
License-File: LICENSE
License-File: NOTICE
